[
    {
        "name": "C112.OBJ",
        "sig": "A0 00 0A 24 08 00 40 01 70 00 09 24 00 00 00 00 ",
        "labels": [
            {
                "name": "_bu_init",
                "offset": 0
            }
        ]
    },
    {
        "name": "C171.OBJ",
        "sig": "A0 00 0A 24 08 00 40 01 AB 00 09 24 00 00 00 00 ",
        "labels": [
            {
                "name": "_card_info",
                "offset": 0
            }
        ]
    },
    {
        "name": "C172.OBJ",
        "sig": "A0 00 0A 24 08 00 40 01 AC 00 09 24 00 00 00 00 ",
        "labels": [
            {
                "name": "_card_load",
                "offset": 0
            }
        ]
    },
    {
        "name": "C173.OBJ",
        "sig": "A0 00 0A 24 08 00 40 01 AD 00 09 24 00 00 00 00 ",
        "labels": [
            {
                "name": "_card_auto",
                "offset": 0
            }
        ]
    },
    {
        "name": "A74.OBJ",
        "sig": "B0 00 0A 24 08 00 40 01 4A 00 09 24 00 00 00 00 ",
        "labels": [
            {
                "name": "InitCARD2",
                "offset": 0
            }
        ]
    },
    {
        "name": "A75.OBJ",
        "sig": "B0 00 0A 24 08 00 40 01 4B 00 09 24 00 00 00 00 ",
        "labels": [
            {
                "name": "StartCARD2",
                "offset": 0
            }
        ]
    },
    {
        "name": "A76.OBJ",
        "sig": "B0 00 0A 24 08 00 40 01 4C 00 09 24 00 00 00 00 ",
        "labels": [
            {
                "name": "StopCARD2",
                "offset": 0
            }
        ]
    },
    {
        "name": "A78.OBJ",
        "sig": "B0 00 0A 24 08 00 40 01 4E 00 09 24 00 00 00 00 ",
        "labels": [
            {
                "name": "_card_write",
                "offset": 0
            }
        ]
    },
    {
        "name": "A79.OBJ",
        "sig": "B0 00 0A 24 08 00 40 01 4F 00 09 24 00 00 00 00 ",
        "labels": [
            {
                "name": "_card_read",
                "offset": 0
            }
        ]
    },
    {
        "name": "A80.OBJ",
        "sig": "B0 00 0A 24 08 00 40 01 50 00 09 24 00 00 00 00 ",
        "labels": [
            {
                "name": "_new_card",
                "offset": 0
            }
        ]
    },
    {
        "name": "A88.OBJ",
        "sig": "B0 00 0A 24 08 00 40 01 58 00 09 24 00 00 00 00 ",
        "labels": [
            {
                "name": "_card_chan",
                "offset": 0
            }
        ]
    },
    {
        "name": "A92.OBJ",
        "sig": "B0 00 0A 24 08 00 40 01 5C 00 09 24 00 00 00 00 ",
        "labels": [
            {
                "name": "_card_status",
                "offset": 0
            }
        ]
    },
    {
        "name": "A93.OBJ",
        "sig": "B0 00 0A 24 08 00 40 01 5D 00 09 24 00 00 00 00 ",
        "labels": [
            {
                "name": "_card_wait",
                "offset": 0
            }
        ]
    },
    {
        "name": "CARD.OBJ",
        "sig": "E8 FF BD 27 10 00 B0 AF 14 00 BF AF ?? ?? ?? 0C 21 80 80 00 21 20 00 02 3F 00 05 24 ?? ?? ?? 0C 21 30 00 00 14 00 BF 8F 10 00 B0 8F 08 00 E0 03 18 00 BD 27 00 00 00 00 00 00 00 00 00 00 00 00 ",
        "labels": [
            {
                "name": "_card_clear",
                "offset": 0
            }
        ]
    },
    {
        "name": "PATCH.OBJ",
        "sig": "0A 00 6F 94 00 00 08 3C 25 C0 E2 01 12 00 19 37 0A 00 79 A4 28 00 08 24 FF FF 08 25 FE FF 00 15 00 00 00 00 08 00 E0 03 00 00 00 00 74 10 62 8C 00 00 00 00 80 00 42 30 0B 00 40 10 00 00 00 00 44 10 62 8C 00 00 00 00 80 00 42 30 FC FF 40 14 00 00 00 00 01 00 02 3C FC DF 42 8C 00 00 00 00 08 00 40 00 00 00 00 00 08 00 E0 03 00 00 00 00 01 A0 02 3C AC DF 42 24 08 00 40 00 00 00 00 00 00 00 00 00 01 A0 08 3C 80 DF 08 25 09 F8 00 01 00 00 00 00 00 00 00 00 ?? ?? 01 3C ?? ?? 3F AC ?? ?? ?? 0C 00 00 00 00 56 00 09 24 B0 00 0A 24 09 F8 40 01 00 00 00 00 18 00 42 8C 00 00 00 00 70 00 43 8C 00 00 00 00 FF FF 69 30 00 4C 09 00 74 00 43 8C 00 00 00 00 FF FF 6A 30 21 18 2A 01 28 00 62 24 ?? ?? 0A 3C ?? ?? 4A 25 ?? ?? 09 3C ?? ?? 29 25 00 00 43 8D 00 00 00 00 00 00 43 AC 04 00 4A 25 FB FF 49 15 04 00 42 24 01 00 01 3C ?? ?? ?? 0C FC DF 22 AC ?? ?? 1F 3C ?? ?? FF 8F 00 00 00 00 08 00 E0 03 00 00 00 00 ?? ?? 01 3C ?? ?? 3F AC ?? ?? ?? 0C 00 00 00 00 57 00 09 24 B0 00 0A 24 09 F8 40 01 00 00 00 00 6C 01 42 8C 00 00 00 00 C8 09 43 8C ?? ?? 0A 3C ?? ?? 4A 25 ?? ?? 09 3C ?? ?? 29 25 00 00 48 8D 00 00 00 00 C8 09 48 AC 04 00 4A 25 FB FF 49 15 04 00 42 24 ?? ?? ?? 0C 00 00 00 00 ?? ?? 1F 3C ?? ?? FF 8F 00 00 00 00 08 00 E0 03 00 00 00 00 80 DF 02 34 ?? ?? 0A 3C ?? ?? 4A 25 ?? ?? 09 3C ?? ?? 29 25 00 00 43 8D 00 00 00 00 00 00 43 AC 04 00 4A 25 FB FF 49 15 04 00 42 24 08 00 E0 03 00 00 00 00 ",
        "labels": [
            {
                "name": "loc_0",
                "offset": 0
            },
            {
                "name": "loc_18",
                "offset": 24
            },
            {
                "name": "loc_40",
                "offset": 64
            },
            {
                "name": "loc_68",
                "offset": 104
            },
            {
                "name": "text_70",
                "offset": 112
            },
            {
                "name": "text_84",
                "offset": 132
            },
            {
                "name": "_patch_card",
                "offset": 152
            },
            {
                "name": "loc_F4",
                "offset": 244
            },
            {
                "name": "_patch_card2",
                "offset": 300
            },
            {
                "name": "loc_168",
                "offset": 360
            },
            {
                "name": "_copy_memcard_patch",
                "offset": 412
            },
            {
                "name": "loc_1B0",
                "offset": 432
            }
        ]
    },
    {
        "name": "INIT.OBJ",
        "sig": "E8 FF BD 27 10 00 B0 AF 21 80 80 00 14 00 BF AF ?? ?? ?? 0C 21 20 00 00 ?? ?? ?? 0C 00 00 00 00 ?? ?? ?? 0C 00 00 00 00 02 00 40 14 00 00 00 00 21 80 00 00 ?? ?? ?? 0C 21 20 00 02 ?? ?? ?? 0C 00 00 00 00 ?? ?? ?? 0C 00 00 00 00 ?? ?? ?? 0C 00 00 00 00 ?? ?? ?? 0C 00 00 00 00 14 00 BF 8F 10 00 B0 8F 08 00 E0 03 18 00 BD 27 E8 FF BD 27 10 00 BF AF ?? ?? ?? 0C 00 00 00 00 ?? ?? ?? 0C 00 00 00 00 ?? ?? ?? 0C 21 20 00 00 ?? ?? ?? 0C 00 00 00 00 10 00 BF 8F 18 00 BD 27 08 00 E0 03 00 00 00 00 E8 FF BD 27 10 00 BF AF ?? ?? ?? 0C 00 00 00 00 ?? ?? ?? 0C 00 00 00 00 10 00 BF 8F 18 00 BD 27 08 00 E0 03 00 00 00 00 00 00 00 00 ",
        "labels": [
            {
                "name": "InitCARD",
                "offset": 0
            },
            {
                "name": "loc_34",
                "offset": 52
            },
            {
                "name": "StartCARD",
                "offset": 108
            },
            {
                "name": "StopCARD",
                "offset": 164
            }
        ]
    },
    {
        "name": "END.OBJ",
        "sig": "?? ?? 01 3C ?? ?? 3F AC ?? ?? ?? 0C 00 00 00 00 56 00 09 24 B0 00 0A 24 09 F8 40 01 00 00 00 00 18 00 42 8C ?? ?? 0A 3C ?? ?? 4A 25 ?? ?? 09 3C ?? ?? 29 25 00 00 43 8D 00 00 00 00 70 00 43 AC 04 00 4A 25 FB FF 49 15 04 00 42 24 ?? ?? ?? 0C 00 00 00 00 ?? ?? ?? 0C 00 00 00 00 ?? ?? 1F 3C ?? ?? FF 8F 00 00 00 00 08 00 E0 03 00 00 00 00 00 00 00 00 00 00 00 00 00 00 00 00 00 00 00 00 ",
        "labels": [
            {
                "name": "_ExitCard",
                "offset": 0
            },
            {
                "name": "loc_34",
                "offset": 52
            },
            {
                "name": "text_70",
                "offset": 112
            },
            {
                "name": "text_7C",
                "offset": 124
            }
        ]
    },
    {
        "name": "FORMAT.OBJ",
        "sig": "50 FF BD 27 90 00 B0 AF 21 80 80 00 A0 00 B4 AF 21 A0 A0 00 9C 00 B3 AF 21 98 C0 00 94 00 B1 AF 21 88 00 00 21 18 60 02 21 28 00 00 7E 00 04 24 A8 00 BF AF A4 00 B5 AF 98 00 B2 AF 00 00 62 90 01 00 63 24 FF FF 84 24 26 10 A2 00 FB FF 81 04 21 28 40 00 00 00 62 A0 01 00 15 24 10 00 B2 27 08 00 22 2A 2E 00 40 10 21 10 00 00 ?? ?? ?? 0C 00 00 00 00 21 20 00 02 21 28 80 02 ?? ?? ?? 0C 21 30 60 02 26 00 55 14 21 10 00 00 ?? ?? ?? 0C 03 21 10 00 01 00 42 30 FC FF 40 10 21 20 40 02 ?? ?? ?? 0C 80 00 05 24 ?? ?? ?? 0C 00 00 00 00 21 20 00 02 21 28 80 02 ?? ?? ?? 0C 21 30 40 02 06 00 55 10 00 00 00 00 ?? ?? 04 3C ?? ?? ?? 0C ?? ?? 84 24 ?? ?? ?? 08 10 00 A4 27 ?? ?? ?? 0C 03 21 10 00 01 00 42 30 FC FF 40 10 10 00 A4 27 21 28 00 00 7E 00 03 24 00 00 82 90 01 00 84 24 FF FF 63 24 FC FF 61 04 26 28 A2 00 7F 00 63 92 FF 00 A2 30 D2 FF 62 14 01 00 31 26 01 00 02 24 A8 00 BF 8F A4 00 B5 8F A0 00 B4 8F 9C 00 B3 8F 98 00 B2 8F 94 00 B1 8F 90 00 B0 8F 08 00 E0 03 B0 00 BD 27 C8 FF BD 27 20 00 B4 AF 21 A0 80 00 18 00 B2 AF 21 90 00 00 1C 00 B3 AF ?? ?? 13 3C ?? ?? 73 26 30 00 BE AF ?? ?? 1E 3C ?? ?? DE 27 2C 00 B7 AF A0 00 17 24 28 00 B6 AF FF FF 16 34 24 00 B5 AF 01 00 15 24 34 00 BF AF 14 00 B1 AF 10 00 B0 AF 21 20 60 02 ?? ?? ?? 0C 80 00 05 24 40 81 12 00 21 88 1E 02 21 20 20 02 ?? ?? ?? 0C 20 00 05 24 ?? ?? 01 3C 21 08 30 00 ?? ?? 37 AC ?? ?? 01 3C 21 08 30 00 ?? ?? 20 AC ?? ?? 01 3C 21 08 30 00 ?? ?? 36 A4 03 00 22 8A 00 00 22 9A 07 00 23 8A 04 00 23 9A 0B 00 24 8A 08 00 24 9A 0F 00 25 8A 0C 00 25 9A 03 00 62 AA 00 00 62 BA 07 00 63 AA 04 00 63 BA 0B 00 64 AA 08 00 64 BA 0F 00 65 AA 0C 00 65 BA 13 00 22 8A 10 00 22 9A 17 00 23 8A 14 00 23 9A 1B 00 24 8A 18 00 24 9A 1F 00 25 8A 1C 00 25 9A 13 00 62 AA 10 00 62 BA 17 00 63 AA 14 00 63 BA 1B 00 64 AA 18 00 64 BA 1F 00 65 AA 1C 00 65 BA 21 20 80 02 01 00 50 26 21 28 00 02 ?? ?? ?? 0C 21 30 60 02 2C 00 55 14 21 10 00 00 21 90 00 02 0F 00 42 2A C6 FF 40 14 21 20 60 02 21 90 00 00 FF FF 15 24 21 88 60 02 01 00 13 24 ?? ?? 10 3C ?? ?? 10 26 00 00 15 AE 21 20 20 02 ?? ?? ?? 0C 80 00 05 24 03 00 02 8A 00 00 02 9A 00 00 00 00 03 00 22 AA 00 00 22 BA 21 20 80 02 10 00 45 26 ?? ?? ?? 0C 21 30 20 02 03 00 53 10 01 00 52 26 ?? ?? ?? 08 21 10 00 00 14 00 42 2A ED FF 40 14 04 00 10 26 21 20 20 02 ?? ?? ?? 0C 80 00 05 24 21 20 80 02 21 28 00 00 21 30 20 02 4D 00 02 24 00 00 C2 A0 43 00 02 24 ?? ?? ?? 0C 01 00 C2 A0 01 00 42 38 01 00 42 2C 34 00 BF 8F 30 00 BE 8F 2C 00 B7 8F 28 00 B6 8F 24 00 B5 8F 20 00 B4 8F 1C 00 B3 8F 18 00 B2 8F 14 00 B1 8F 10 00 B0 8F 08 00 E0 03 38 00 BD 27 ",
        "labels": [
            {
                "name": "loc_0",
                "offset": 0
            },
            {
                "name": "loc_3C",
                "offset": 60
            },
            {
                "name": "loc_60",
                "offset": 96
            },
            {
                "name": "loc_8C",
                "offset": 140
            },
            {
                "name": "loc_DC",
                "offset": 220
            },
            {
                "name": "text_F0",
                "offset": 240
            },
            {
                "name": "loc_F8",
                "offset": 248
            },
            {
                "name": "loc_120",
                "offset": 288
            },
            {
                "name": "_card_format",
                "offset": 324
            },
            {
                "name": "loc_198",
                "offset": 408
            },
            {
                "name": "loc_29C",
                "offset": 668
            },
            {
                "name": "loc_2E0",
                "offset": 736
            },
            {
                "name": "text_320",
                "offset": 800
            }
        ]
    }
]